ycombinator_scraper/__init__.py
ycombinator_scraper/__main__.py
ycombinator_scraper/cli.py
ycombinator_scraper/config.py
ycombinator_scraper/exceptions.py
ycombinator_scraper/models.py
ycombinator_scraper/py.typed
ycombinator_scraper/scraper.py
ycombinator_scraper/selectors.py
ycombinator_scraper/utils.py
ycombinator_scraper-0.7.4.dist-info/LICENSE
ycombinator_scraper-0.7.4.dist-info/METADATA
ycombinator_scraper-0.7.4.dist-info/WHEEL
ycombinator_scraper-0.7.4.dist-info/entry_points.txt
ycombinator_scraper-0.7.4.dist-info/top_level.txt
ycombinator_scraper-0.7.4.dist-info/RECORD
