Metadata-Version: 2.1
Name: ycombinator-scraper
Version: 0.7.4
Summary: A Python command-line tool and package for scraping company, job, and founder data from Workatastartup.com
Author-email: Ifeanyi Nneji <ifeanyinneji777@gmail.com>
License: MIT License
Project-URL: Homepage, https://github.com/Nneji123/ycombinator-scraper
Project-URL: Documentation, https://Nneji23.github.io/ycombinator-scraper
Project-URL: Repository, https://github.com/Nneji123/ycombinator-scraper
Project-URL: Say Thanks!, https://saythanks.io/to/Nneji123
Project-URL: Source, https://github.com/Nneji123/ycombinator-scraper
Classifier: Development Status :: 4 - Beta
Classifier: Environment :: Console
Classifier: Intended Audience :: Developers
Classifier: License :: OSI Approved :: MIT License
Classifier: Programming Language :: Python
Classifier: Programming Language :: Python :: 3
Classifier: Programming Language :: Python :: 3 :: Only
Classifier: Programming Language :: Python :: 3.9
Classifier: Programming Language :: Python :: 3.10
Classifier: Programming Language :: Python :: 3.11
Classifier: Programming Language :: Python :: 3.12
Classifier: Topic :: Software Development :: Libraries :: Python Modules
Classifier: Topic :: Utilities
Classifier: Natural Language :: English
Classifier: License :: OSI Approved :: MIT License
Classifier: Operating System :: OS Independent
Classifier: Typing :: Typed
Classifier: Framework :: Pydantic
Classifier: Topic :: Software Development :: Libraries :: Application Frameworks
Classifier: Topic :: Software Development :: Libraries :: Python Modules
Classifier: Topic :: Internet :: WWW/HTTP :: Browsers
Classifier: Topic :: Internet :: WWW/HTTP :: Indexing/Search
Classifier: Topic :: Internet :: WWW/HTTP :: Site Management
Classifier: Topic :: Software Development :: Libraries
Requires-Python: >=3.9
License-File: LICENSE
Requires-Dist: click >=8.1.7
Requires-Dist: beautifulsoup4 >=4.12.3
Requires-Dist: loguru >=0.7.2
Requires-Dist: pandas >=2.2.0
Requires-Dist: pathlib >=1.0.1
Requires-Dist: pydantic >=2.5.3
Requires-Dist: pydantic-settings >=2.1.0
Requires-Dist: selenium >=4.17.2
Requires-Dist: webdriver-manager >=4.0.1
